qoolqit/__init__.py
qoolqit/drive.py
qoolqit/exceptions.py
qoolqit/program.py
qoolqit/register.py
qoolqit/utils.py
qoolqit/devices/__init__.py
qoolqit/devices/device.py
qoolqit/devices/unit_converter.py
qoolqit/embedding/__init__.py
qoolqit/embedding/base_embedder.py
qoolqit/embedding/graph_embedder.py
qoolqit/embedding/matrix_embedder.py
qoolqit/embedding/algorithms/__init__.py
qoolqit/embedding/algorithms/interaction_embedding.py
qoolqit/embedding/algorithms/spring_layout_embedding.py
qoolqit/execution/__init__.py
qoolqit/execution/backends.py
qoolqit/execution/compilation_functions.py
qoolqit/execution/sequence_compiler.py
qoolqit/execution/utils.py
qoolqit/graphs/__init__.py
qoolqit/graphs/base_graph.py
qoolqit/graphs/data_graph.py
qoolqit/graphs/utils.py
qoolqit/waveforms/__init__.py
qoolqit/waveforms/base_waveforms.py
qoolqit/waveforms/utils.py
qoolqit/waveforms/waveforms.py
qoolqit-0.3.2.dist-info/METADATA
qoolqit-0.3.2.dist-info/WHEEL
qoolqit-0.3.2.dist-info/licenses/LICENSE
qoolqit-0.3.2.dist-info/RECORD
