Metadata-Version: 2.4
Name: qoolqit
Version: 0.3.2
Summary: A Python library for developing algorithms in the Rydberg Analog Model.
Project-URL: Documentation, https://pasqal-io.github.io/qoolqit/latest
Project-URL: Issues, https://github.com/pasqal-io/qoolqit/issues
Project-URL: Source, https://github.com/pasqal-io/qoolqit
Author-email: João Moutinho <joao.moutinho@pasqal.com>, Stefano Grava <s.grava-ext@pasqal.com>, Vytautas Abramavicius <vytautas.abramavicius@pasqal.com>, Roland Guichard <roland.guichard@pasqal.com>, David Teller <david.teller@pasqal.com>, Manu Lahariya <manu.lahariya@pasqal.com>, Charles MOUSSA <charles.moussa@pasqal.com>, Vittorio Vitale <vittorio.vitale@pasqal.com>
License: MIT-derived
License-File: LICENSE
Keywords: quantum
Classifier: Development Status :: 3 - Alpha
Classifier: Programming Language :: Python
Classifier: Programming Language :: Python :: 3.10
Classifier: Programming Language :: Python :: 3.11
Classifier: Programming Language :: Python :: 3.12
Classifier: Programming Language :: Python :: 3.13
Classifier: Programming Language :: Python :: Implementation :: CPython
Classifier: Programming Language :: Python :: Implementation :: PyPy
Requires-Python: >=3.10
Requires-Dist: emu-mps
Requires-Dist: emu-sv
Requires-Dist: networkx~=3.4
Requires-Dist: pasqal-cloud>=0.20.6
Requires-Dist: pulser~=1.6.2
Provides-Extra: docs
Requires-Dist: markdown-exec; extra == 'docs'
Requires-Dist: mike; extra == 'docs'
Requires-Dist: mkapi; extra == 'docs'
Requires-Dist: mkdocs; extra == 'docs'
Requires-Dist: mkdocs-exclude; extra == 'docs'
Requires-Dist: mkdocs-jupyter==0.24.7; extra == 'docs'
Requires-Dist: mkdocs-material; extra == 'docs'
Requires-Dist: mkdocs-section-index; extra == 'docs'
Requires-Dist: mkdocstrings; extra == 'docs'
Requires-Dist: mkdocstrings-python; extra == 'docs'
Provides-Extra: extras
Requires-Dist: black; extra == 'extras'
Requires-Dist: flaky; extra == 'extras'
Requires-Dist: ipykernel; extra == 'extras'
Requires-Dist: isort; extra == 'extras'
Requires-Dist: jupyter; extra == 'extras'
Requires-Dist: nbconvert; extra == 'extras'
Requires-Dist: nbmake; extra == 'extras'
Requires-Dist: pre-commit; extra == 'extras'
Requires-Dist: pydocstringformatter; extra == 'extras'
Requires-Dist: pytest; extra == 'extras'
Requires-Dist: pytest-cov; extra == 'extras'
Requires-Dist: pytest-markdown-docs; extra == 'extras'
Requires-Dist: pytest-repeat; extra == 'extras'
Requires-Dist: ruff; extra == 'extras'
Requires-Dist: torch-geometric; extra == 'extras'
